yt_concate/__init__.py
yt_concate/main.py
yt_concate/setting.py
yt_concate/utils.py
yt_concate/model/__init__.py
yt_concate/model/found.py
yt_concate/model/yt.py
yt_concate/pipeline/__init__.py
yt_concate/pipeline/pipeline.py
yt_concate/pipeline/steps/__init__.py
yt_concate/pipeline/steps/download_captions.py
yt_concate/pipeline/steps/download_videos.py
yt_concate/pipeline/steps/edit_video.py
yt_concate/pipeline/steps/get_video_list.py
yt_concate/pipeline/steps/initialize_yt.py
yt_concate/pipeline/steps/postflight.py
yt_concate/pipeline/steps/preflight.py
yt_concate/pipeline/steps/read_caption.py
yt_concate/pipeline/steps/search.py
yt_concate/pipeline/steps/step.py
yt_concate_beta-0.1.2.dist-info/LICENSE
yt_concate_beta-0.1.2.dist-info/METADATA
yt_concate_beta-0.1.2.dist-info/WHEEL
yt_concate_beta-0.1.2.dist-info/top_level.txt
yt_concate_beta-0.1.2.dist-info/RECORD
